Basic_gates/full_adder.v
module full_adder (
    input a,b,cin,
    output s,cout
);

assign s = a ^ b ^ cin;
assign cout = (a & b) | (b & cin) | (a & cin);

endmodule

First_Class/full_adder_tb.v
`timescale 1ps/1ps  

module full_adder_tb;

reg a,b,cin;
wire s,cout;

full_adder uut (
    .a(a),
    .b(b),
    .cin(cin),
    .s(s),
    .cout(cout)
);

initial begin

$monitor("Time=%0t | A=%b B=%b Cin=%b | S=%b Cout=%b", $time, a, b, cin, s, cout);

// $dumpfile("full_adder.vcd");
// $dumpvars(0, full_adder_tb);

a = 0; b = 0; cin = 0; #10;    
a = 0; b = 0; cin = 1; #10;
a = 0; b = 1; cin = 0; #10;
a = 0; b = 1; cin = 1; #10;
a = 1; b = 0; cin = 0; #10;
a = 1; b = 0; cin = 1; #10;
a = 1; b = 1; cin = 0; #10;
a = 1; b = 1; cin = 1; #10;
$finish;

end
endmodule

Basic_gates/full_adder.vcd
$date
	Sun Aug 30 11:26:23 2026
$end
$version
	Icarus Verilog
$end
$timescale
	1ps
$end
$scope module full_adder_tb $end
$var wire 1 ! s $end
$var wire 1 " cout $end
$var reg 1 # a $end
$var reg 1 $ b $end
$var reg 1 % cin $end
$scope module uut $end
$var wire 1 # a $end
$var wire 1 $ b $end
$var wire 1 % cin $end
$var wire 1 " cout $end
$var wire 1 ! s $end
$upscope $end
$upscope $end
$enddefinitions $end
$comment Show the parameter values. $end
$dumpall
$end
#0
$dumpvars
0%
0$
0#
0"
0!
$end
#10
1!
1%
#20
0%
1$
#30
1"
0!
1%
#40
0"
1!
0%
0$
1#
#50
1"
0!
1%
#60
0%
1$
#70
1!
1%
